awslogs_sd/__init__.py
awslogs_sd/awslogs_sd.py
awslogs_sd/metrics.py
awslogs_sd-0.5.dist-info/DESCRIPTION.rst
awslogs_sd-0.5.dist-info/METADATA
awslogs_sd-0.5.dist-info/RECORD
awslogs_sd-0.5.dist-info/WHEEL
awslogs_sd-0.5.dist-info/entry_points.txt
awslogs_sd-0.5.dist-info/metadata.json
awslogs_sd-0.5.dist-info/top_level.txt
awslogs_sd-0.5.dist-info/zip-safe
