Metadata-Version: 2.0
Name: awslogs-sd
Version: 0.5
Summary: Forward systemd journal logs to cloudwatch
Home-page: https://github.com/mbachry/awslogs-sd
Author: Marcin Bachry
Author-email: hegel666@gmail.com
License: MIT
Platform: UNKNOWN
Classifier: Development Status :: 4 - Beta
Classifier: Intended Audience :: Developers
Classifier: License :: OSI Approved :: MIT License
Classifier: Natural Language :: English
Classifier: Programming Language :: Python :: 3
Classifier: Programming Language :: Python :: 3.5
Classifier: Programming Language :: Python :: 3.6
Requires-Dist: awscli-cwlogs
Requires-Dist: boto3
Requires-Dist: gevent
Requires-Dist: pyyaml
Requires-Dist: requests
Requires-Dist: retrying
Requires-Dist: systemd-python
